<?xml version="1.0" encoding="utf-8"?>
<!--
/*
** Copyright 2012, SAMSUNG
** Author: Nagarjuna Thottempudi(nagarjuna.t@samsung.com)
*/
-->

<!-- use empty string wherever values are not present -->

<mccota version="5">
    <ad country="Afghanistan"
		 mcc="412"
		 idd="00"
		 ndd="0"
		 nanp=""
		 nbpcd="0"
		 countrycode="93"
		 sid="14976 to 15103"
		 gmt="4.5"
		 gmtdst="4.5"
		 sidconflict=""
	/>

	<ad country="Albania"
		 mcc="276"
		 idd="00"
		 ndd="0"
		 nanp=""
		 nbpcd="0"
		 countrycode="355"
		 sid="31456 to 31471"
		 gmt="1"
		 gmtdst="2"
		 sidconflict=""
	/>

	<ad country="Algeria"
		 mcc="603"
		 idd="00"
		 ndd="0"
		 nanp=""
		 nbpcd="0"
		 countrycode="213"
		 sid="8288 to 8319"
		 gmt="1"
		 gmtdst="1"
		 sidconflict="8294"
	/>

	<ad country="American Samoa (US)"
		 mcc="544"
		 idd="011"
		 ndd="1"
		 nanp="NANP"
		 nbpcd="0"
		 countrycode="1"
		 sid="n/a"
		 gmt="-11"
		 gmtdst="-11"
		 sidconflict="4100"
	/>

	<ad country="Andorra"
		 mcc="213"
		 idd="00"
		 ndd="None"
		 nanp=""
		 nbpcd="0"
		 countrycode="376"
		 sid="n/a"
		 gmt="1"
		 gmtdst="2"
		 sidconflict=""
	/>

	<ad country="Angola"
		 mcc="631"
		 idd="00"
		 ndd="0"
		 nanp=""
		 nbpcd="0"
		 countrycode="244"
		 sid="9504 to 9535"
		 gmt="1"
		 gmtdst="1"
		 sidconflict=""
	/>

	<ad country="Anguilla"
		 mcc="365"
		 idd="011"
		 ndd="1"
		 nanp="NANP"
		 nbpcd="0"
		 countrycode="1"
		 sid="n/a"
		 gmt="-4"
		 gmtdst="-4"
		 sidconflict=""
	/>

	<ad country="Antigua and Barbuda"
		 mcc="344"
		 idd="011"
		 ndd="1"
		 nanp="NANP"
		 nbpcd="0"
		 countrycode="1"
		 sid="8144 to 8159"
		 gmt="-4"
		 gmtdst="-4"
		 sidconflict=""
	/>

	<ad country="Argentina"
		 mcc="722"
		 idd="00"
		 ndd="0"
		 nanp=""
		 nbpcd="0"
		 countrycode="54"
		 sid="32128 to 32255"
		 gmt="-3"
		 gmtdst="-2"
		 sidconflict=""
	/>

	<ad country="Armenia"
		 mcc="283"
		 idd="00"
		 ndd="0"
		 nanp=""
		 nbpcd="0"
		 countrycode="374"
		 sid="n/a"
		 gmt="4"
		 gmtdst="5"
		 sidconflict=""
	/>

	<ad country="Aruba"
		 mcc="363"
		 idd="00"
		 ndd="None"
		 nanp=""
		 nbpcd="0"
		 countrycode="297"
		 sid="9648 to 9663"
		 gmt="-4"
		 gmtdst="-4"
		 sidconflict="12978"
	/>

	<ad country="Australia"
		 mcc="505"
		 idd="0011"
		 ndd="0"
		 nanp=""
		 nbpcd="0"
		 countrycode="61"
		 sid="7680 to 7807	8320 to 8447"
		 gmt="8 to 10.5"
		 gmtdst="9 to 11.5"
		 sidconflict="8358	8360"
	/>

	<ad country="Austria"
		 mcc="232"
		 idd="00"
		 ndd="0"
		 nanp=""
		 nbpcd="0"
		 countrycode="43"
		 sid="22912 to 23039"
		 gmt="1"
		 gmtdst="2"
		 sidconflict=""
	/>

	<ad country="Azerbaijani Republic"
		 mcc="400"
		 idd="00"
		 ndd="0"
		 nanp=""
		 nbpcd="0"
		 countrycode="994"
		 sid="n/a"
		 gmt="4"
		 gmtdst="5"
		 sidconflict=""
	/>

	<ad country="Bahamas"
		 mcc="364"
		 idd="011"
		 ndd="1"
		 nanp="NANP"
		 nbpcd="0"
		 countrycode="1"
		 sid="8080 to 8095"
		 gmt="-5"
		 gmtdst="-4"
		 sidconflict="32752"
	/>

	<ad country="Bahrain"
		 mcc="426"
		 idd="00"
		 ndd="None"
		 nanp=""
		 nbpcd="0"
		 countrycode="973"
		 sid="31408 to 31423"
		 gmt="3"
		 gmtdst="3"
		 sidconflict=""
	/>

	<ad country="Bangladesh"
		 mcc="470"
		 idd="00"
		 ndd="0"
		 nanp=""
		 nbpcd="1"
		 countrycode="880"
		 sid="13472 to 13503"
		 gmt="6"
		 gmtdst="6"
		 sidconflict="12461	12463	12464"
	/>

	<ad country="Barbados"
		 mcc="342"
		 idd="011"
		 ndd="1"
		 nanp="NANP"
		 nbpcd="0"
		 countrycode="1"
		 sid="8160 to 8175"
		 gmt="-4"
		 gmtdst="-4"
		 sidconflict=""
	/>

	<ad country="Belarus"
		 mcc="257"
		 idd="810"
		 ndd="8"
		 nanp=""
		 nbpcd="0"
		 countrycode="375"
		 sid="n/a"
		 gmt="2"
		 gmtdst="3"
		 sidconflict=""
	/>

	<ad country="Belgium"
		 mcc="206"
		 idd="00"
		 ndd="0"
		 nanp=""
		 nbpcd="0"
		 countrycode="32"
		 sid="23936 to 24063"
		 gmt="1"
		 gmtdst="2"
		 sidconflict=""
	/>

	<ad country="Belize"
		 mcc="702"
		 idd="00"
		 ndd="None"
		 nanp=""
		 nbpcd="0"
		 countrycode="501"
		 sid="32640 to 32649"
		 gmt="-6"
		 gmtdst="-6"
		 sidconflict=""
	/>

	<ad country="Benin"
		 mcc="616"
		 idd="00"
		 ndd="None"
		 nanp=""
		 nbpcd="0"
		 countrycode="229"
		 sid="9088 to 9119"
		 gmt="1"
		 gmtdst="1"
		 sidconflict=""
	/>

	<ad country="Bermuda (UK)"
		 mcc="350"
		 idd="011"
		 ndd="1"
		 nanp="NANP"
		 nbpcd="0"
		 countrycode="1"
		 sid="n/a"
		 gmt="1"
		 gmtdst="2"
		 sidconflict="8198"
	/>

	<ad country="Bhutan"
		 mcc="402"
		 idd="00"
		 ndd="None"
		 nanp=""
		 nbpcd="0"
		 countrycode="975"
		 sid="n/a"
		 gmt="6"
		 gmtdst="6"
		 sidconflict=""
	/>

	<ad country="Bolivia"
		 mcc="736"
		 idd="00"
		 ndd="0"
		 nanp=""
		 nbpcd="0"
		 countrycode="591"
		 sid="31232 to 31263"
		 gmt="-4"
		 gmtdst="-4"
		 sidconflict=""
	/>

	<ad country="Bosnia and Herzegovina"
		 mcc="218"
		 idd="00"
		 ndd="0"
		 nanp=""
		 nbpcd="0"
		 countrycode="387"
		 sid="n/a"
		 gmt="1"
		 gmtdst="2"
		 sidconflict=""
	/>

	<ad country="Botswana"
		 mcc="652"
		 idd="00"
		 ndd="None"
		 nanp=""
		 nbpcd="0"
		 countrycode="267"
		 sid="10176 to 10207"
		 gmt="2"
		 gmtdst="2"
		 sidconflict=""
	/>

	<ad country="Brazil"
		 mcc="724"
		 idd="0015"
		 ndd="0"
		 nanp=""
		 nbpcd="0"
		 countrycode="55"
		 sid="31872 to 32127"
		 gmt="-2 to -4"
		 gmtdst="-2 to -5"
		 sidconflict="3	23	27	29	33	43	47	61	65	67	69	71	131	257	259	261	263	320	322	326	328	330	387	389	389	391	395	576	582	703	739	1218	1220	1222	1282	1313	1315	1329	1409	1443	1521	1569	1581	1634	1666	1668"
	/>

	<ad country="British Virgin Islands (UK)"
		 mcc="348"
		 idd="011"
		 ndd="1"
		 nanp="NANP"
		 nbpcd="1"
		 countrycode="1"
		 sid="8112 to 8127"
		 gmt="-4"
		 gmtdst="-4"
		 sidconflict=""
	/>

	<ad country="Brunei Darussalam"
		 mcc="528"
		 idd="00"
		 ndd="None"
		 nanp=""
		 nbpcd="0"
		 countrycode="673"
		 sid="10880 to 10895"
		 gmt="8"
		 gmtdst="8"
		 sidconflict=""
	/>

	<ad country="Bulgaria"
		 mcc="284"
		 idd="00"
		 ndd="0"
		 nanp=""
		 nbpcd="0"
		 countrycode="359"
		 sid="15584 to 15615"
		 gmt="2"
		 gmtdst="3"
		 sidconflict=""
	/>

	<ad country="Burkina Faso"
		 mcc="613"
		 idd="00"
		 ndd="None"
		 nanp=""
		 nbpcd="0"
		 countrycode="226"
		 sid="8992 to 9023"
		 gmt="0"
		 gmtdst="0"
		 sidconflict=""
	/>

	<ad country="Burundi"
		 mcc="642"
		 idd="00"
		 ndd="None"
		 nanp=""
		 nbpcd="0"
		 countrycode="257"
		 sid="9952 to 9983"
		 gmt="2"
		 gmtdst="2"
		 sidconflict=""
	/>

	<ad country="Cambodia"
		 mcc="456"
		 idd="001"
		 ndd="0"
		 nanp=""
		 nbpcd="0"
		 countrycode="855"
		 sid="11104 to 11135"
		 gmt="7"
		 gmtdst="7"
		 sidconflict=""
	/>

	<ad country="Cameroon"
		 mcc="624"
		 idd="00"
		 ndd="None"
		 nanp=""
		 nbpcd="0"
		 countrycode="237"
		 sid="9344 to 9375"
		 gmt="1"
		 gmtdst="1"
		 sidconflict=""
	/>

	<ad country="Canada"
		 mcc="302"
		 idd="011"
		 ndd="1"
		 nanp="NANP"
		 nbpcd="0"
		 countrycode="1"
		 sid="16384 to 18431"
		 gmt="-3.5 to -8"
		 gmtdst="-2.5 to -8"
		 sidconflict=""
	/>

	<ad country="Cape Verde"
		 mcc="625"
		 idd="0"
		 ndd="None"
		 nanp=""
		 nbpcd="0"
		 countrycode="238"
		 sid="8848 to 8863"
		 gmt="-1"
		 gmtdst="-1"
		 sidconflict="8860	8861	8863"
	/>

	<ad country="Cayman Islands (UK)"
		 mcc="346"
		 idd="011"
		 ndd="1"
		 nanp="NANP"
		 nbpcd="0"
		 countrycode="1"
		 sid="8128 to 8143"
		 gmt="-5"
		 gmtdst="-5"
		 sidconflict=""
	/>

	<ad country="Central African Republic"
		 mcc="623"
		 idd="00"
		 ndd="None"
		 nanp=""
		 nbpcd="0"
		 countrycode="238"
		 sid="9312 to 9343"
		 gmt="1"
		 gmtdst="1"
		 sidconflict="9322"
	/>

	<ad country="Chad"
		 mcc="622"
		 idd="15"
		 ndd="None"
		 nanp=""
		 nbpcd="0"
		 countrycode="235"
		 sid="9280 to 9311"
		 gmt="1"
		 gmtdst="1"
		 sidconflict=""
	/>

	<ad country="Chile"
		 mcc="730"
		 idd="00"
		 ndd="0"
		 nanp=""
		 nbpcd="0"
		 countrycode="56"
		 sid="31744 to 31754	31809 to 31820	31841 to 31854"
		 gmt="-4"
		 gmtdst="-3"
		 sidconflict=""
	/>

	<ad country="China"
		 mcc="460"
		 idd="00"
		 ndd="0"
		 nanp=""
		 nbpcd=""
		 countrycode="86"
		 sid="13568 to 14335	25600 to 26111"
		 gmt="8"
		 gmtdst="8"
		 sidconflict=""
	/>

	<ad country="Colombia"
		 mcc="732"
		 idd="00"
		 ndd="None"
		 nanp=""
		 nbpcd="0"
		 countrycode="57"
		 sid="31616 to 31743"
		 gmt="-5"
		 gmtdst="-5"
		 sidconflict=""
	/>

	<ad country="Comoros"
		 mcc="654"
		 idd="00"
		 ndd="None"
		 nanp=""
		 nbpcd="0"
		 countrycode="269"
		 sid="10208 to 10239"
		 gmt="3"
		 gmtdst="3"
		 sidconflict=""
	/>

	<ad country="Cook Islands (NZ)"
		 mcc="548"
		 idd="00"
		 ndd="None"
		 nanp=""
		 nbpcd="0"
		 countrycode="682"
		 sid="11136 to 11151"
		 gmt="-10"
		 gmtdst=""
		 sidconflict=""
	/>

	<ad country="Costa Rica"
		 mcc="712"
		 idd="00"
		 ndd="None"
		 nanp=""
		 nbpcd="0"
		 countrycode="506"
		 sid="32544 to 32575"
		 gmt="-6"
		 gmtdst=""
		 sidconflict=""
	/>

	<ad country="Cote d'Ivoire"
		 mcc="612"
		 idd="00"
		 ndd="None"
		 nanp=""
		 nbpcd="0"
		 countrycode="225"
		 sid="8960 to 8991"
		 gmt="0"
		 gmtdst="0"
		 sidconflict="8960	8962"
	/>

	<ad country="Croatia"
		 mcc="219"
		 idd="00"
		 ndd="0"
		 nanp=""
		 nbpcd="0"
		 countrycode="385"
		 sid="n/a"
		 gmt="1"
		 gmtdst="2"
		 sidconflict=""
	/>

	<ad country="Cuba"
		 mcc="368"
		 idd="119"
		 ndd="0"
		 nanp=""
		 nbpcd="0"
		 countrycode="53"
		 sid="32256 to 32383"
		 gmt="-5"
		 gmtdst="-4"
		 sidconflict=""
	/>

	<ad country="Cyprus"
		 mcc="280"
		 idd="00"
		 ndd="None"
		 nanp=""
		 nbpcd="0"
		 countrycode="357"
		 sid="31200 to 31231"
		 gmt="2"
		 gmtdst="3"
		 sidconflict=""
	/>

	<ad country="Czech Republic"
		 mcc="230"
		 idd="00"
		 ndd="None"
		 nanp=""
		 nbpcd="0"
		 countrycode="420"
		 sid="16128 to 16255"
		 gmt="1"
		 gmtdst="2"
		 sidconflict=""
	/>

	<ad country="Democratic Republic of the Congo"
		 mcc="630"
		 idd="00"
		 ndd="0"
		 nanp=""
		 nbpcd="0"
		 countrycode="243"
		 sid="9440 to 9471"
		 gmt="1 to 2 "
		 gmtdst="1 to 2 "
		 sidconflict=""
	/>

	<ad country="Denmark"
		 mcc="238"
		 idd="00"
		 ndd="None"
		 nanp=""
		 nbpcd="0"
		 countrycode="45"
		 sid="22528 to 22543"
		 gmt="1"
		 gmtdst="2"
		 sidconflict=""
	/>

	<ad country="Djibouti"
		 mcc="638"
		 idd="00"
		 ndd="None"
		 nanp=""
		 nbpcd="0"
		 countrycode="253"
		 sid="8912 to 8927"
		 gmt="3"
		 gmtdst="3"
		 sidconflict=""
	/>

	<ad country="Dominica"
		 mcc="366"
		 idd="011"
		 ndd="1"
		 nanp="NANP"
		 nbpcd="0"
		 countrycode="1"
		 sid="9616 to 9631"
		 gmt="-4"
		 gmtdst="-4"
		 sidconflict=""
	/>

	<ad country="Dominican Republic"
		 mcc="370"
		 idd="011"
		 ndd="1"
		 nanp="NANP"
		 nbpcd="0"
		 countrycode="1"
		 sid="8832 to 8847"
		 gmt="-4"
		 gmtdst="-4"
		 sidconflict=""
	/>

	<ad country="East Timor"
		 mcc="514"
		 idd="00"
		 ndd="None"
		 nanp=""
		 nbpcd="0"
		 countrycode="670"
		 sid="n/a"
		 gmt="9"
		 gmtdst="9"
		 sidconflict=""
	/>

	<ad country="Ecuador"
		 mcc="740"
		 idd="00"
		 ndd="0"
		 nanp=""
		 nbpcd="0"
		 countrycode="593"
		 sid="31296 to 31327"
		 gmt="-5"
		 gmtdst="-5"
		 sidconflict=""
	/>

	<ad country="Egypt"
		 mcc="602"
		 idd="00"
		 ndd="0"
		 nanp=""
		 nbpcd="0"
		 countrycode="20"
		 sid="8224 to 8255"
		 gmt="2"
		 gmtdst="3"
		 sidconflict=""
	/>

	<ad country="El Salvador"
		 mcc="706"
		 idd="00"
		 ndd="None"
		 nanp=""
		 nbpcd="0"
		 countrycode="593"
		 sid="32704 to 32735"
		 gmt="-6"
		 gmtdst="-6"
		 sidconflict=""
	/>

	<ad country="Equatorial Guinea"
		 mcc="627"
		 idd="00"
		 ndd="None"
		 nanp=""
		 nbpcd="0"
		 countrycode="240"
		 sid="9376 to 9407"
		 gmt="1"
		 gmtdst="1"
		 sidconflict="9394"
	/>

	<ad country="Eritrea"
		 mcc="657"
		 idd="00"
		 ndd="00"
		 nanp=""
		 nbpcd="0"
		 countrycode="291"
		 sid="n/a"
		 gmt="3"
		 gmtdst="3"
		 sidconflict=""
	/>

	<ad country="Estonia"
		 mcc="248"
		 idd="00"
		 ndd="None"
		 nanp=""
		 nbpcd="0"
		 countrycode="372"
		 sid="10872 to 10879"
		 gmt="2"
		 gmtdst="3"
		 sidconflict=""
	/>

	<ad country="Ethiopia"
		 mcc="636"
		 idd="00"
		 ndd="0"
		 nanp=""
		 nbpcd="0"
		 countrycode="251"
		 sid="9760 to 9791"
		 gmt="3"
		 gmtdst="3"
		 sidconflict="9788	9790"
	/>

	<ad country="Faroe Islands (Denmark)"
		 mcc="288"
		 idd="00"
		 ndd="None"
		 nanp=""
		 nbpcd="0"
		 countrycode="298"
		 sid="7936 to 7951"
		 gmt="0"
		 gmtdst="1"
		 sidconflict=""
	/>

	<ad country="Federated States of Micronesia"
		 mcc="550"
		 idd="011"
		 ndd="1"
		 nanp=""
		 nbpcd="0"
		 countrycode="691"
		 sid="11040 to 11071"
		 gmt="10"
		 gmtdst="11"
		 sidconflict=""
	/>

	<ad country="Fiji"
		 mcc="542"
		 idd="00"
		 ndd="None"
		 nanp=""
		 nbpcd="0"
		 countrycode="679"
		 sid="10960 to 10975"
		 gmt="12"
		 gmtdst="12"
		 sidconflict=""
	/>

	<ad country="Finland"
		 mcc="244"
		 idd="00"
		 ndd="0"
		 nanp=""
		 nbpcd="0"
		 countrycode="358"
		 sid="24448 to 24451"
		 gmt="2"
		 gmtdst="3"
		 sidconflict=""
	/>

	<ad country="France"
		 mcc="208"
		 idd="00"
		 ndd="0"
		 nanp=""
		 nbpcd="0"
		 countrycode="33"
		 sid="23680 to 23935"
		 gmt="1"
		 gmtdst="2"
		 sidconflict=""
	/>

	<ad country="French Guiana (France)"
		 mcc="742"
		 idd="00"
		 ndd="None"
		 nanp=""
		 nbpcd="0"
		 countrycode="594"
		 sid="31328 to 31359"
		 gmt="-4"
		 gmtdst="-4"
		 sidconflict=""
	/>

	<ad country="French Polynesia (France)"
		 mcc="547"
		 idd="00"
		 ndd="None"
		 nanp=""
		 nbpcd="0"
		 countrycode="689"
		 sid="11248 to 11263"
		 gmt="-10"
		 gmtdst="-10"
		 sidconflict=""
	/>

	<ad country="Gabonese Republic"
		 mcc="628"
		 idd="00"
		 ndd="None"
		 nanp=""
		 nbpcd="0"
		 countrycode="241"
		 sid="9408 to 9439"
		 gmt="1"
		 gmtdst="1"
		 sidconflict=""
	/>

	<ad country="Gambia"
		 mcc="607"
		 idd="00"
		 ndd="None"
		 nanp=""
		 nbpcd="0"
		 countrycode="220"
		 sid="8544 to 8575"
		 gmt="0"
		 gmtdst="0"
		 sidconflict=""
	/>

	<ad country="Georgia"
		 mcc="282"
		 idd="810"
		 ndd="8"
		 nanp=""
		 nbpcd="0"
		 countrycode="995"
		 sid="n/a"
		 gmt="4"
		 gmtdst="4"
		 sidconflict=""
	/>

	<ad country="Germany"
		 mcc="262"
		 idd="00"
		 ndd="0"
		 nanp=""
		 nbpcd="0"
		 countrycode="49"
		 sid="22016 to 22271"
		 gmt="1"
		 gmtdst="2"
		 sidconflict=""
	/>

	<ad country="Ghana"
		 mcc="620"
		 idd="00"
		 ndd="0"
		 nanp=""
		 nbpcd="0"
		 countrycode="233"
		 sid="9216 to 9247"
		 gmt="0"
		 gmtdst="0"
		 sidconflict="9244	9426"
	/>

	<ad country="Gibraltar (UK)"
		 mcc="266"
		 idd="00"
		 ndd="None"
		 nanp=""
		 nbpcd="0"
		 countrycode="350"
		 sid="31440 to 31455"
		 gmt="1"
		 gmtdst="2"
		 sidconflict=""
	/>

	<ad country="Greece"
		 mcc="202"
		 idd="00"
		 ndd="0"
		 nanp=""
		 nbpcd="0"
		 countrycode="30"
		 sid="24192 to 24319"
		 gmt="2"
		 gmtdst="3"
		 sidconflict=""
	/>

	<ad country="Greenland (Denmark)"
		 mcc="290"
		 idd="00"
		 ndd="None"
		 nanp=""
		 nbpcd="0"
		 countrycode="299"
		 sid="7952 to 7967"
		 gmt="0 to -4"
		 gmtdst="0 to -4"
		 sidconflict=""
	/>

	<ad country="Grenada"
		 mcc="352"
		 idd="011"
		 ndd="1"
		 nanp="NANP"
		 nbpcd="0"
		 countrycode="1"
		 sid="8064 to 8079"
		 gmt="-4"
		 gmtdst="-4"
		 sidconflict=""
	/>

	<ad country="Guadeloupe (France)"
		 mcc="340"
		 idd="00"
		 ndd="None"
		 nanp=""
		 nbpcd="0"
		 countrycode="590"
		 sid="31360 to 31375"
		 gmt="-4"
		 gmtdst="-4"
		 sidconflict=""
	/>

	<ad country="Guam (US)"
		 mcc="535"
		 idd="011"
		 ndd="1"
		 nanp="NANP"
		 nbpcd="0"
		 countrycode="1"
		 sid="9696 to 9711"
		 gmt="10"
		 gmtdst="10"
		 sidconflict=""
	/>

	<ad country="Guatemala"
		 mcc="704"
		 idd="00"
		 ndd="None"
		 nanp=""
		 nbpcd="0"
		 countrycode="502"
		 sid="32672 to 32703"
		 gmt="-6"
		 gmtdst="-6"
		 sidconflict=""
	/>

	<ad country="Guinea"
		 mcc="611"
		 idd="00"
		 ndd="None"
		 nanp=""
		 nbpcd="0"
		 countrycode="224"
		 sid="8800 to 8831"
		 gmt="0"
		 gmtdst="0"
		 sidconflict=""
	/>

	<ad country="Guinea-Bissau"
		 mcc="632"
		 idd="00"
		 ndd="None"
		 nanp=""
		 nbpcd="0"
		 countrycode="245"
		 sid="8800 to 8831"
		 gmt="0"
		 gmtdst="0"
		 sidconflict="9562"
	/>

	<ad country="Guyana"
		 mcc="738"
		 idd="001"
		 ndd="None"
		 nanp=""
		 nbpcd="0"
		 countrycode="592"
		 sid="31264 to 31295"
		 gmt="-4"
		 gmtdst="-4"
		 sidconflict=""
	/>

	<ad country="Haiti"
		 mcc="372"
		 idd="00"
		 ndd="None"
		 nanp=""
		 nbpcd="0"
		 countrycode="509"
		 sid="32608 to 32639"
		 gmt="-5"
		 gmtdst="-5"
		 sidconflict=""
	/>

	<ad country="Honduras"
		 mcc="708"
		 idd="00"
		 ndd="None"
		 nanp=""
		 nbpcd="0"
		 countrycode="504"
		 sid="32736 to 32767"
		 gmt="-6"
		 gmtdst="-6"
		 sidconflict="32752"
	/>

	<ad country="Hong Kong (PRC)"
		 mcc="454"
		 idd="001"
		 ndd="None"
		 nanp=""
		 nbpcd="1"
		 countrycode="852"
		 sid="10640 to 10655"
		 gmt="8"
		 gmtdst="8"
		 sidconflict="13"
	/>

	<ad country="Hungary"
		 mcc="216"
		 idd="00"
		 ndd="06"
		 nanp=""
		 nbpcd="0"
		 countrycode="36"
		 sid="15744 to 15871"
		 gmt="1"
		 gmtdst="2"
		 sidconflict=""
	/>

	<ad country="Iceland"
		 mcc="274"
		 idd="00"
		 ndd="None"
		 nanp=""
		 nbpcd="0"
		 countrycode="354"
		 sid="24416 to 24447"
		 gmt="0"
		 gmtdst="0"
		 sidconflict=""
	/>

	<ad country="India(404)"
		 mcc="404"
		 idd="00"
		 ndd="0"
		 nanp=""
		 nbpcd="0"
		 countrycode="91"
		 sid="14464 to 14847"
		 gmt="5.5"
		 gmtdst="5.5"
		 sidconflict="1	2	7	2222	14850"
	/>

	<ad country="India(405)"
		 mcc="405"
		 idd="00"
		 ndd="0"
		 nanp=""
		 nbpcd="0"
		 countrycode="91"
		 sid="14464 to 14847"
		 gmt="5.5"
		 gmtdst="5.5"
		 sidconflict="1	2	7	2222"
	/>

	<ad country="Indonesia"
		 mcc="510"
		 idd="001"
		 ndd="0"
		 nanp=""
		 nbpcd="0"
		 countrycode="62"
		 sid="10496 to 10623"
		 gmt="7 to 9"
		 gmtdst="7 to 9"
		 sidconflict=""
	/>

	<ad country="Iran"
		 mcc="432"
		 idd="00"
		 ndd="0"
		 nanp=""
		 nbpcd="0"
		 countrycode="98"
		 sid="15616 to 15743"
		 gmt="3.5"
		 gmtdst="4.5"
		 sidconflict=""
	/>

	<ad country="Iraq"
		 mcc="418"
		 idd="00"
		 ndd="0"
		 nanp=""
		 nbpcd="0"
		 countrycode="964"
		 sid="15456 to 15487"
		 gmt="3"
		 gmtdst="3"
		 sidconflict=""
	/>

	<ad country="Ireland"
		 mcc="272"
		 idd="00"
		 ndd="0"
		 nanp=""
		 nbpcd="0"
		 countrycode="353"
		 sid="24384 to 24387"
		 gmt="0"
		 gmtdst="1"
		 sidconflict=""
	/>

	<ad country="Israel"
		 mcc="425"
		 idd="00"
		 ndd="0"
		 nanp=""
		 nbpcd="0"
		 countrycode="972"
		 sid="8448 to 8479"
		 gmt="2"
		 gmtdst="3"
		 sidconflict=""
	/>

	<ad country="Italy"
		 mcc="222"
		 idd="00"
		 ndd="None"
		 nanp=""
		 nbpcd="0"
		 countrycode="39"
		 sid="23168 to 23423"
		 gmt="1"
		 gmtdst="2"
		 sidconflict=""
	/>

	<ad country="Jamaica"
		 mcc="338"
		 idd="011"
		 ndd="1"
		 nanp="NANP"
		 nbpcd="1"
		 countrycode="1"
		 sid="8176 to 8191"
		 gmt="-5"
		 gmtdst="-5"
		 sidconflict=""
	/>

	<ad country="Japan"
		 mcc="440"
		 idd="010"
		 ndd="0"
		 nanp=""
		 nbpcd="0"
		 countrycode="81"
		 sid="12288 to 13311"
		 gmt="9"
		 gmtdst="9"
		 sidconflict="12461	12463	12464	12978	12561"
	/>

	<ad country="Japan"
		 mcc="441"
		 idd="010"
		 ndd="0"
		 nanp=""
		 nbpcd="0"
		 countrycode="81"
		 sid="12288 to 13311"
		 gmt="9"
		 gmtdst="9"
		 sidconflict=""
	/>

	<ad country="Jordan"
		 mcc="416"
		 idd="00"
		 ndd="0"
		 nanp=""
		 nbpcd="0"
		 countrycode="962"
		 sid="15392 to 15423"
		 gmt="2"
		 gmtdst="3"
		 sidconflict=""
	/>

	<ad country="Kazakhstan"
		 mcc="401"
		 idd="810"
		 ndd="8"
		 nanp=""
		 nbpcd="0"
		 countrycode="7"
		 sid="8928 to 8943"
		 gmt="5 to 6"
		 gmtdst="5 to 6"
		 sidconflict=""
	/>

	<ad country="Kenya"
		 mcc="639"
		 idd="00"
		 ndd="0"
		 nanp=""
		 nbpcd="0"
		 countrycode="254"
		 sid="9856 to 9887"
		 gmt="3"
		 gmtdst="3"
		 sidconflict=""
	/>

	<ad country="Kiribati"
		 mcc="545"
		 idd="00"
		 ndd="None"
		 nanp=""
		 nbpcd="0"
		 countrycode="686"
		 sid="11200 to 11215"
		 gmt="12 to 14"
		 gmtdst="12 to 14"
		 sidconflict=""
	/>

	<ad country="Korea, North"
		 mcc="467"
		 idd="00"
		 ndd="0"
		 nanp=""
		 nbpcd="0"
		 countrycode="850"
		 sid="11072 to 11103"
		 gmt="9"
		 gmtdst="9"
		 sidconflict=""
	/>

	<ad country="Korea, South"
		 mcc="450"
		 idd="00700"
		 ndd="0"
		 nanp=""
		 nbpcd="0"
		 countrycode="82"
		 sid="2176 to 2303"
		 gmt="9"
		 gmtdst="9"
		 sidconflict="1111	1112	1113	1700	2177	2179	2181	2183	2185	2187	2189	2191	2193	2195	2197	2199	2201	2203	2205	2207	2209	2211	2213	2215	2217	2219	2221	2222	2223	2225	2227	2229	2231	2233	2235	2237	2239	2241	2243	2301	2303	4369	4370	4371"
	/>

	<ad country="Kuwait"
		 mcc="419"
		 idd="00"
		 ndd="None"
		 nanp=""
		 nbpcd="0"
		 countrycode="965"
		 sid="11312 to 11327"
		 gmt="3"
		 gmtdst="3"
		 sidconflict=""
	/>

	<ad country="Kyrgyz Republic"
		 mcc="437"
		 idd="00"
		 ndd="0"
		 nanp=""
		 nbpcd="0"
		 countrycode="996"
		 sid="21550 to 21566"
		 gmt="6"
		 gmtdst="6"
		 sidconflict=""
	/>

	<ad country="Laos"
		 mcc="457"
		 idd="00"
		 ndd="0"
		 nanp=""
		 nbpcd="0"
		 countrycode="856"
		 sid="13440 to 13471"
		 gmt="7"
		 gmtdst="7"
		 sidconflict=""
	/>

	<ad country="Latvia"
		 mcc="247"
		 idd="00"
		 ndd="None"
		 nanp=""
		 nbpcd="0"
		 countrycode="371"
		 sid="10784 to 10785"
		 gmt="2"
		 gmtdst="3"
		 sidconflict=""
	/>

	<ad country="Lebanon"
		 mcc="415"
		 idd="00"
		 ndd="0"
		 nanp=""
		 nbpcd="0"
		 countrycode="961"
		 sid="15360 to 15391"
		 gmt="2"
		 gmtdst="3"
		 sidconflict=""
	/>

	<ad country="Lesotho"
		 mcc="651"
		 idd="00"
		 ndd="None"
		 nanp=""
		 nbpcd="0"
		 countrycode="266"
		 sid="9600 to 9615"
		 gmt="2"
		 gmtdst="2"
		 sidconflict=""
	/>

	<ad country="Liberia"
		 mcc="618"
		 idd="00"
		 ndd="None"
		 nanp=""
		 nbpcd="0"
		 countrycode="231"
		 sid="9152 to 9183"
		 gmt="0"
		 gmtdst="0"
		 sidconflict=""
	/>

	<ad country="Libya"
		 mcc="606"
		 idd="00"
		 ndd="0"
		 nanp=""
		 nbpcd="0"
		 countrycode="218"
		 sid="8512 to 8543"
		 gmt="2"
		 gmtdst="2"
		 sidconflict=""
	/>

	<ad country="Liechtenstein"
		 mcc="295"
		 idd="00"
		 ndd="None"
		 nanp=""
		 nbpcd="0"
		 countrycode="423"
		 sid="n/a"
		 gmt="1"
		 gmtdst="2"
		 sidconflict=""
	/>

	<ad country="Lithuania"
		 mcc="246"
		 idd="00"
		 ndd="0"
		 nanp=""
		 nbpcd="0"
		 countrycode="370"
		 sid="n/a"
		 gmt="2"
		 gmtdst="3"
		 sidconflict=""
	/>

	<ad country="Luxembourg"
		 mcc="270"
		 idd="00"
		 ndd="None"
		 nanp=""
		 nbpcd="0"
		 countrycode="352"
		 sid="24352 to 24383"
		 gmt="1"
		 gmtdst="2"
		 sidconflict=""
	/>

	<ad country="Macao (PRC)"
		 mcc="455"
		 idd="00"
		 ndd="None"
		 nanp=""
		 nbpcd="0"
		 countrycode="853"
		 sid="11296 to 11311"
		 gmt="8"
		 gmtdst="8"
		 sidconflict=""
	/>

	<ad country="Madagascar"
		 mcc="646"
		 idd="00"
		 ndd="None"
		 nanp=""
		 nbpcd="0"
		 countrycode="261"
		 sid="10048 to 10079"
		 gmt="3"
		 gmtdst="3"
		 sidconflict=""
	/>

	<ad country="Malawi"
		 mcc="650"
		 idd="00"
		 ndd="None"
		 nanp=""
		 nbpcd="0"
		 countrycode="265"
		 sid="10144 to 10175"
		 gmt="2"
		 gmtdst="2"
		 sidconflict=""
	/>

	<ad country="Malaysia"
		 mcc="502"
		 idd="00"
		 ndd="0"
		 nanp=""
		 nbpcd="0"
		 countrycode="60"
		 sid="10368 to 10495"
		 gmt="8"
		 gmtdst="8"
		 sidconflict=""
	/>

	<ad country="Maldives"
		 mcc="472"
		 idd="00"
		 ndd="None"
		 nanp=""
		 nbpcd="0"
		 countrycode="960"
		 sid="13536 to 13567"
		 gmt="5"
		 gmtdst="5"
		 sidconflict=""
	/>

	<ad country="Mali"
		 mcc="610"
		 idd="00"
		 ndd="None"
		 nanp=""
		 nbpcd="0"
		 countrycode="223"
		 sid="8768 to 8799"
		 gmt="0"
		 gmtdst="0"
		 sidconflict=""
	/>

	<ad country="Malta"
		 mcc="278"
		 idd="00"
		 ndd="None"
		 nanp=""
		 nbpcd="0"
		 countrycode="356"
		 sid="31472 to 31475"
		 gmt="1"
		 gmtdst="2"
		 sidconflict=""
	/>

	<ad country="Marshall Islands"
		 mcc="551"
		 idd="011"
		 ndd="1"
		 nanp=""
		 nbpcd="0"
		 countrycode="692"
		 sid="11280 to 11295"
		 gmt="12"
		 gmtdst="12"
		 sidconflict=""
	/>

	<ad country="Martinique (France)"
		 mcc="340"
		 idd="00"
		 ndd="None"
		 nanp=""
		 nbpcd="0"
		 countrycode="596"
		 sid="31376 to 31391"
		 gmt="-4"
		 gmtdst="-4"
		 sidconflict=""
	/>

	<ad country="Mauritania"
		 mcc="609"
		 idd="00"
		 ndd="None"
		 nanp=""
		 nbpcd="0"
		 countrycode="222"
		 sid="8736 to 8767"
		 gmt="0"
		 gmtdst="0"
		 sidconflict=""
	/>

	<ad country="Mauritius"
		 mcc="617"
		 idd="020"
		 ndd="None"
		 nanp=""
		 nbpcd="0"
		 countrycode="230"
		 sid="9120 to 9151"
		 gmt="4"
		 gmtdst="5"
		 sidconflict=""
	/>

	<ad country="Mexico"
		 mcc="334"
		 idd="00"
		 ndd="01"
		 nanp=""
		 nbpcd="0"
		 countrycode="52"
		 sid="24576 to 25075	25100 to 25124"
		 gmt="-8 to -6"
		 gmtdst="-8 to -6"
		 sidconflict="1525"
	/>

	<ad country="Moldova"
		 mcc="259"
		 idd="00"
		 ndd="0"
		 nanp=""
		 nbpcd="0"
		 countrycode="373"
		 sid="15922 to 15937"
		 gmt="2"
		 gmtdst="3"
		 sidconflict=""
	/>

	<ad country="Monaco"
		 mcc="212"
		 idd="00"
		 ndd="None"
		 nanp=""
		 nbpcd="0"
		 countrycode="377"
		 sid="10752 to 10767"
		 gmt="1"
		 gmtdst="2"
		 sidconflict=""
	/>

	<ad country="Mongolia"
		 mcc="428"
		 idd="001"
		 ndd="0"
		 nanp=""
		 nbpcd="0"
		 countrycode="976"
		 sid="15520 to 15551"
		 gmt="7 to 8"
		 gmtdst="7 to 8"
		 sidconflict=""
	/>

	<ad country="Montserrat (UK)"
		 mcc="354"
		 idd="011"
		 ndd="1"
		 nanp="NANP"
		 nbpcd="0"
		 countrycode="1"
		 sid="8048 to 8063"
		 gmt="-4"
		 gmtdst="-4"
		 sidconflict=""
	/>

	<ad country="Morocco"
		 mcc="604"
		 idd="00"
		 ndd="0"
		 nanp=""
		 nbpcd="0"
		 countrycode="212"
		 sid="8256 to 8287"
		 gmt="0"
		 gmtdst="1"
		 sidconflict=""
	/>

	<ad country="Mozambique"
		 mcc="643"
		 idd="00"
		 ndd="None"
		 nanp=""
		 nbpcd="0"
		 countrycode="258"
		 sid="9984 to 10015"
		 gmt="2"
		 gmtdst="2"
		 sidconflict=""
	/>

	<ad country="Myanmar"
		 mcc="414"
		 idd="00"
		 ndd="0"
		 nanp=""
		 nbpcd="0"
		 countrycode="95"
		 sid="15232 to 15359"
		 gmt="6.5"
		 gmtdst="6.5"
		 sidconflict=""
	/>

	<ad country="Namibia"
		 mcc="649"
		 idd="00"
		 ndd="0"
		 nanp=""
		 nbpcd="0"
		 countrycode="264"
		 sid="10112 to 10143"
		 gmt="1"
		 gmtdst="2"
		 sidconflict=""
	/>

	<ad country="Nauru"
		 mcc="536"
		 idd="00"
		 ndd="None"
		 nanp=""
		 nbpcd="0"
		 countrycode="674"
		 sid="10896 to 10911"
		 gmt="12"
		 gmtdst="12"
		 sidconflict=""
	/>

	<ad country="Nepal"
		 mcc="429"
		 idd="00"
		 ndd="0"
		 nanp=""
		 nbpcd="0"
		 countrycode="977"
		 sid="15552 to 15583"
		 gmt="5.75"
		 gmtdst="5.75"
		 sidconflict=""
	/>

	<ad country="Netherlands"
		 mcc="204"
		 idd="00"
		 ndd="0"
		 nanp=""
		 nbpcd="0"
		 countrycode="31"
		 sid="24064 to 24191"
		 gmt="1"
		 gmtdst="2"
		 sidconflict=""
	/>

	<ad country="Netherlands Antilles (Netherlands)"
		 mcc="362"
		 idd="00"
		 ndd="0"
		 nanp=""
		 nbpcd="0"
		 countrycode="599"
		 sid="31392 to 31407"
		 gmt="-4"
		 gmtdst="-4"
		 sidconflict="136"
	/>

	<ad country="New Caledonia (France)"
		 mcc="546"
		 idd="00"
		 ndd="None"
		 nanp=""
		 nbpcd="0"
		 countrycode="687"
		 sid="11216 to 11231"
		 gmt="11"
		 gmtdst="11"
		 sidconflict=""
	/>

	<ad country="New Zealand"
		 mcc="530"
		 idd="00"
		 ndd="0"
		 nanp=""
		 nbpcd="1"
		 countrycode="64"
		 sid="8576 to 8703"
		 gmt="12"
		 gmtdst="13"
		 sidconflict="8616"
	/>

	<ad country="Nicaragua"
		 mcc="710"
		 idd="00"
		 ndd="None"
		 nanp=""
		 nbpcd="0"
		 countrycode="505"
		 sid="32512 to 32543"
		 gmt="-6"
		 gmtdst="-6"
		 sidconflict=""
	/>

	<ad country="Niger"
		 mcc="614"
		 idd="00"
		 ndd="None"
		 nanp=""
		 nbpcd="0"
		 countrycode="227"
		 sid="9024 to 9055"
		 gmt="1"
		 gmtdst="1"
		 sidconflict=""
	/>

	<ad country="Nigeria"
		 mcc="621"
		 idd="009"
		 ndd="0"
		 nanp=""
		 nbpcd="0"
		 countrycode="234"
		 sid="9248 to 9279"
		 gmt="1"
		 gmtdst="1"
		 sidconflict="111	211	311"
	/>

	<ad country="Northern Mariana Islands, Saipan (US)"
		 mcc="534"
		 idd="011"
		 ndd="1"
		 nanp=""
		 nbpcd="0"
		 countrycode="1"
		 sid="9680 to 9695"
		 gmt="10"
		 gmtdst="10"
		 sidconflict=""
	/>

	<ad country="Norway"
		 mcc="242"
		 idd="00"
		 ndd="None"
		 nanp=""
		 nbpcd="0"
		 countrycode="47"
		 sid="22272 to 22399"
		 gmt="1"
		 gmtdst="2"
		 sidconflict=""
	/>

	<ad country="Oman"
		 mcc="422"
		 idd="00"
		 ndd="None"
		 nanp=""
		 nbpcd="0"
		 countrycode="968"
		 sid="11344 to 11359"
		 gmt="4"
		 gmtdst="4"
		 sidconflict=""
	/>

	<ad country="Pakistan"
		 mcc="410"
		 idd="00"
		 ndd="0"
		 nanp=""
		 nbpcd="0"
		 countrycode="92"
		 sid="14848 to 14975"
		 gmt="5"
		 gmtdst="6"
		 sidconflict="14850"
	/>

	<ad country="Palau"
		 mcc="552"
		 idd="11"
		 ndd="None"
		 nanp=""
		 nbpcd="0"
		 countrycode="680"
		 sid="10976 to 10991"
		 gmt="9"
		 gmtdst="9"
		 sidconflict=""
	/>

	<ad country="Panama"
		 mcc="714"
		 idd="00"
		 ndd="None"
		 nanp=""
		 nbpcd="0"
		 countrycode="507"
		 sid="32576 to 32607"
		 gmt="-5"
		 gmtdst="-5"
		 sidconflict=""
	/>

	<ad country="Papua New Guinea"
		 mcc="537"
		 idd="5"
		 ndd="None"
		 nanp=""
		 nbpcd="0"
		 countrycode="675"
		 sid="11008 to 11039"
		 gmt="10"
		 gmtdst="10"
		 sidconflict=""
	/>

	<ad country="Paraguay"
		 mcc="744"
		 idd="2"
		 ndd="0"
		 nanp=""
		 nbpcd="0"
		 countrycode="595"
		 sid="31104 to 31135"
		 gmt="-4"
		 gmtdst="-3"
		 sidconflict=""
	/>

	<ad country="Peru"
		 mcc="716"
		 idd="00"
		 ndd="0"
		 nanp=""
		 nbpcd="0"
		 countrycode="51"
		 sid="32384 to 32511"
		 gmt="-5"
		 gmtdst="-5"
		 sidconflict=""
	/>

	<ad country="Philippines"
		 mcc="515"
		 idd="00"
		 ndd="0"
		 nanp=""
		 nbpcd="0"
		 countrycode="63"
		 sid="10624 to 10639	10656 to 10751"
		 gmt="8"
		 gmtdst="8"
		 sidconflict="1235"
	/>

	<ad country="Poland"
		 mcc="260"
		 idd="00"
		 ndd="0"
		 nanp=""
		 nbpcd="0"
		 countrycode="48"
		 sid="16256 to 16271	16272 to 16383"
		 gmt="1"
		 gmtdst="2"
		 sidconflict=""
	/>

	<ad country="Portugal"
		 mcc="268"
		 idd="00"
		 ndd="None"
		 nanp=""
		 nbpcd="0"
		 countrycode="351"
		 sid="24320 to 24351"
		 gmt="0"
		 gmtdst="1"
		 sidconflict=""
	/>

	<ad country="Puerto Rico (US)"
		 mcc="330"
		 idd="011"
		 ndd="1"
		 nanp="NANP"
		 nbpcd="0"
		 countrycode="1"
		 sid="n/a"
		 gmt="-4"
		 gmtdst="-4"
		 sidconflict=""
	/>

	<ad country="Qatar"
		 mcc="427"
		 idd="00"
		 ndd="None"
		 nanp=""
		 nbpcd="0"
		 countrycode="974"
		 sid="31424 to 31439"
		 gmt="3"
		 gmtdst="3"
		 sidconflict=""
	/>

	<ad country="Republic of Macedonia"
		 mcc="294"
		 idd="00"
		 ndd="0"
		 nanp=""
		 nbpcd="0"
		 countrycode="389"
		 sid="n/a"
		 gmt="1"
		 gmtdst="2"
		 sidconflict=""
	/>

	<ad country="Republic of the Congo"
		 mcc="629"
		 idd="00"
		 ndd="None"
		 nanp=""
		 nbpcd="0"
		 countrycode="243"
		 sid="9440 to 9471"
		 gmt="1"
		 gmtdst="1"
		 sidconflict=""
	/>

	<ad country="Reunion (France)"
		 mcc="647"
		 idd="00"
		 ndd="0"
		 nanp=""
		 nbpcd="0"
		 countrycode="262"
		 sid="8944 to 8959"
		 gmt="4"
		 gmtdst="4"
		 sidconflict="89500	8952"
	/>

	<ad country="Romania"
		 mcc="226"
		 idd="00"
		 ndd="0"
		 nanp=""
		 nbpcd="0"
		 countrycode="40"
		 sid="16000 to 16127"
		 gmt="2"
		 gmtdst="3"
		 sidconflict=""
	/>

	<ad country="Russian Federation"
		 mcc="250"
		 idd="810"
		 ndd="8"
		 nanp=""
		 nbpcd="0"
		 countrycode="7"
		 sid="11392 to 11554	11556 to 11599	11601 to 12287"
		 gmt="2 to 12"
		 gmtdst="3  to 13"
		 sidconflict="1901"
	/>

	<ad country="Rwandese Republic"
		 mcc="635"
		 idd="00"
		 ndd="None"
		 nanp=""
		 nbpcd="0"
		 countrycode="250"
		 sid="9728 to 9759"
		 gmt="2"
		 gmtdst="2"
		 sidconflict=""
	/>

	<ad country="Saint Kitts and Nevis"
		 mcc="356"
		 idd="011"
		 ndd="1"
		 nanp="NANP"
		 nbpcd="0"
		 countrycode="1"
		 sid="8032 to 8047"
		 gmt="-4"
		 gmtdst="-4"
		 sidconflict=""
	/>

	<ad country="Saint Lucia"
		 mcc="358"
		 idd="011"
		 ndd="1"
		 nanp="NANP"
		 nbpcd="0"
		 countrycode="1"
		 sid="8016 to 8031"
		 gmt="-4"
		 gmtdst="-4"
		 sidconflict=""
	/>

	<ad country="Saint Pierre and Miquelon (France)"
		 mcc="308"
		 idd="00"
		 ndd="None"
		 nanp=""
		 nbpcd="0"
		 countrycode="508"
		 sid="7984 to 7999	10816 to 10831"
		 gmt="-3"
		 gmtdst="-2"
		 sidconflict=""
	/>

	<ad country="Saint Vincent and the Grenadines"
		 mcc="360"
		 idd="011"
		 ndd="1"
		 nanp="NANP"
		 nbpcd="0"
		 countrycode="1"
		 sid="8000 to 8007"
		 gmt="-4"
		 gmtdst="-4"
		 sidconflict=""
	/>

	<ad country="Samoa"
		 mcc="549"
		 idd="0"
		 ndd="None"
		 nanp=""
		 nbpcd="0"
		 countrycode="685"
		 sid="11184 to 11199"
		 gmt="-11"
		 gmtdst="-11"
		 sidconflict=""
	/>

	<ad country="San Marino"
		 mcc="292"
		 idd="00"
		 ndd="None"
		 nanp=""
		 nbpcd="0"
		 countrycode="378"
		 sid="10768 to 10783"
		 gmt="1"
		 gmtdst="2"
		 sidconflict=""
	/>

	<ad country="Sao Tome and Principe"
		 mcc="626"
		 idd="00"
		 ndd="None"
		 nanp=""
		 nbpcd="0"
		 countrycode="239"
		 sid="8864 to 8879"
		 gmt="0"
		 gmtdst="0"
		 sidconflict=""
	/>

	<ad country="Saudi Arabia"
		 mcc="420"
		 idd="00"
		 ndd="0"
		 nanp=""
		 nbpcd="0"
		 countrycode="966"
		 sid="15488 to 15519"
		 gmt="3"
		 gmtdst="3"
		 sidconflict=""
	/>

	<ad country="Senegal"
		 mcc="608"
		 idd="00"
		 ndd="None"
		 nanp=""
		 nbpcd="0"
		 countrycode="221"
		 sid="8704 to 8735"
		 gmt="0"
		 gmtdst="0"
		 sidconflict=""
	/>

	<ad country="Serbia and Montenegro"
		 mcc="220"
		 idd="99"
		 ndd="0"
		 nanp=""
		 nbpcd="0"
		 countrycode="381"
		 sid="23424 to 23551"
		 gmt="1"
		 gmtdst="1"
		 sidconflict=""
	/>

	<ad country="Seychelles"
		 mcc="633"
		 idd="00"
		 ndd="None"
		 nanp=""
		 nbpcd="0"
		 countrycode="248"
		 sid="8896 to 8911"
		 gmt="4"
		 gmtdst="4"
		 sidconflict=""
	/>

	<ad country="Sierra Leone"
		 mcc="619"
		 idd="00"
		 ndd="0"
		 nanp=""
		 nbpcd="0"
		 countrycode="232"
		 sid="9184 to 9215"
		 gmt="0"
		 gmtdst="0"
		 sidconflict="9212"
	/>

	<ad country="Singapore"
		 mcc="525"
		 idd="001"
		 ndd="None"
		 nanp=""
		 nbpcd="0"
		 countrycode="65"
		 sid="9664 to 9679"
		 gmt="8"
		 gmtdst="8"
		 sidconflict="12561"
	/>

	<ad country="Slovakia"
		 mcc="231"
		 idd="00"
		 ndd="0"
		 nanp=""
		 nbpcd="0"
		 countrycode="421"
		 sid="n/a"
		 gmt="1"
		 gmtdst="2"
		 sidconflict=""
	/>

	<ad country="Slovenia"
		 mcc="293"
		 idd="00"
		 ndd="0"
		 nanp=""
		 nbpcd="0"
		 countrycode="386"
		 sid="n/a"
		 gmt="1"
		 gmtdst="2"
		 sidconflict=""
	/>

	<ad country="Solomon Islands"
		 mcc="540"
		 idd="00"
		 ndd="None"
		 nanp=""
		 nbpcd="0"
		 countrycode="677"
		 sid="10928 to 10943"
		 gmt="11"
		 gmtdst="11"
		 sidconflict=""
	/>

	<ad country="Somalia"
		 mcc="637"
		 idd="00"
		 ndd="None"
		 nanp=""
		 nbpcd="0"
		 countrycode="252"
		 sid="9792 to 9823"
		 gmt="3"
		 gmtdst="3"
		 sidconflict=""
	/>

	<ad country="South Africa"
		 mcc="655"
		 idd="00"
		 ndd="0"
		 nanp=""
		 nbpcd="0"
		 countrycode="27"
		 sid="10240 to 10367"
		 gmt="2"
		 gmtdst="2"
		 sidconflict=""
	/>

	<ad country="Spain"
		 mcc="214"
		 idd="00"
		 ndd="None"
		 nanp=""
		 nbpcd="0"
		 countrycode="34"
		 sid="23552 to 23679"
		 gmt="1"
		 gmtdst="2"
		 sidconflict=""
	/>

	<ad country="Sri Lanka"
		 mcc="413"
		 idd="00"
		 ndd="0"
		 nanp=""
		 nbpcd="0"
		 countrycode="94"
		 sid="15104 to 15231"
		 gmt="5.5"
		 gmtdst="5.5"
		 sidconflict=""
	/>

	<ad country="Sudan"
		 mcc="634"
		 idd="00"
		 ndd="0"
		 nanp=""
		 nbpcd="0"
		 countrycode="249"
		 sid="9568 to 9599"
		 gmt="3"
		 gmtdst="3"
		 sidconflict=""
	/>

	<ad country="Suriname"
		 mcc="746"
		 idd="00"
		 ndd="0"
		 nanp=""
		 nbpcd="0"
		 countrycode="597"
		 sid="31136 to 31167"
		 gmt="-3"
		 gmtdst="-3"
		 sidconflict=""
	/>

	<ad country="Swaziland"
		 mcc="653"
		 idd="00"
		 ndd="None"
		 nanp=""
		 nbpcd="0"
		 countrycode="268"
		 sid="9632 to 9647"
		 gmt="2"
		 gmtdst="2"
		 sidconflict="9640	9642	9644"
	/>

	<ad country="Sweden"
		 mcc="240"
		 idd="00"
		 ndd="0"
		 nanp=""
		 nbpcd="0"
		 countrycode="46"
		 sid="22400 to 22403"
		 gmt="1"
		 gmtdst="2"
		 sidconflict=""
	/>

	<ad country="Switzerland"
		 mcc="228"
		 idd="00"
		 ndd="0"
		 nanp=""
		 nbpcd="0"
		 countrycode="41"
		 sid="23040 to 23167"
		 gmt="1"
		 gmtdst="2"
		 sidconflict=""
	/>

	<ad country="Syria"
		 mcc="417"
		 idd="00"
		 ndd="0"
		 nanp=""
		 nbpcd="0"
		 countrycode="963"
		 sid="15424 to 15455"
		 gmt="2"
		 gmtdst="3"
		 sidconflict=""
	/>

	<ad country="Taiwan"
		 mcc="466"
		 idd="002"
		 ndd="0"
		 nanp=""
		 nbpcd="0"
		 countrycode="886"
		 sid="13504 to 13535"
		 gmt="8"
		 gmtdst="8"
		 sidconflict=""
	/>

	<ad country="Tajikistan"
		 mcc="436"
		 idd="810"
		 ndd="8"
		 nanp=""
		 nbpcd="0"
		 countrycode="992"
		 sid="10856 to 10871"
		 gmt="5"
		 gmtdst="5"
		 sidconflict=""
	/>

	<ad country="Tanzania"
		 mcc="640"
		 idd="000"
		 ndd="0"
		 nanp=""
		 nbpcd="0"
		 countrycode="255"
		 sid="9888 to 9919"
		 gmt="3"
		 gmtdst="3"
		 sidconflict=""
	/>

	<ad country="Thailand"
		 mcc="520"
		 idd="001"
		 ndd="0"
		 nanp=""
		 nbpcd="0"
		 countrycode="66"
		 sid="8192 to 8223"
		 gmt="7"
		 gmtdst="7"
		 sidconflict="8198"
	/>

	<ad country="Togolese Republic"
		 mcc="615"
		 idd="00"
		 ndd="None"
		 nanp=""
		 nbpcd="0"
		 countrycode="228"
		 sid="9056 to 9087"
		 gmt="0"
		 gmtdst="0"
		 sidconflict="9080"
	/>

	<ad country="Tonga"
		 mcc="539"
		 idd="00"
		 ndd="None"
		 nanp=""
		 nbpcd="0"
		 countrycode="676"
		 sid="10912 to 10927"
		 gmt="13"
		 gmtdst="13"
		 sidconflict=""
	/>

	<ad country="Trinidad and Tobago"
		 mcc="374"
		 idd="011"
		 ndd="1"
		 nanp="NANP"
		 nbpcd="0"
		 countrycode="1"
		 sid="9824 to 9855"
		 gmt="-4"
		 gmtdst="-4"
		 sidconflict=""
	/>

	<ad country="Tunisia"
		 mcc="605"
		 idd="00"
		 ndd="None"
		 nanp=""
		 nbpcd="0"
		 countrycode="216"
		 sid="8480 to 8511"
		 gmt="1"
		 gmtdst="2"
		 sidconflict=""
	/>

	<ad country="Turkey"
		 mcc="286"
		 idd="00"
		 ndd="0"
		 nanp=""
		 nbpcd="0"
		 countrycode="90"
		 sid="14336 to 14463"
		 gmt="2"
		 gmtdst="3"
		 sidconflict=""
	/>

	<ad country="Turkmenistan"
		 mcc="438"
		 idd="810"
		 ndd="8"
		 nanp=""
		 nbpcd="0"
		 countrycode="993"
		 sid="n/a"
		 gmt="5"
		 gmtdst="5"
		 sidconflict=""
	/>

	<ad country="Turks and Caicos Islands (UK)"
		 mcc="376"
		 idd="011"
		 ndd="1"
		 nanp="NANP"
		 nbpcd="0"
		 countrycode="1"
		 sid="10800 to 10815"
		 gmt="-5"
		 gmtdst="-4"
		 sidconflict=""
	/>

	<ad country="Uganda"
		 mcc="641"
		 idd="000"
		 ndd="0"
		 nanp=""
		 nbpcd="0"
		 countrycode="256"
		 sid="9920 to 9951"
		 gmt="3"
		 gmtdst="3"
		 sidconflict=""
	/>

	<ad country="Ukraine"
		 mcc="255"
		 idd="810"
		 ndd="0"
		 nanp=""
		 nbpcd="0"
		 countrycode="380"
		 sid="15906 to 15921"
		 gmt="2"
		 gmtdst="3"
		 sidconflict=""
	/>

	<ad country="United Arab Emirates(424)"
		 mcc="424"
		 idd="00"
		 ndd="0"
		 nanp=""
		 nbpcd="0"
		 countrycode="971"
		 sid="11376 to 11391"
		 gmt="4"
		 gmtdst="4"
		 sidconflict=""
	/>

	<ad country="United Arab Emirates(430)"
		 mcc="430 to 431"
		 idd="00"
		 ndd="0"
		 nanp=""
		 nbpcd="0"
		 countrycode="971"
		 sid="11376 to 11391"
		 gmt="4"
		 gmtdst="4"
		 sidconflict=""
	/>

	<ad country="United Kingdom(234)"
		 mcc="234"
		 idd="00"
		 ndd="0"
		 nanp=""
		 nbpcd="0"
		 countrycode="44"
		 sid="22656 to 22911"
		 gmt="0"
		 gmtdst="1"
		 sidconflict=""
	/>

	<ad country="United Kingdom(235)"
		 mcc="235"
		 idd="00"
		 ndd="0"
		 nanp=""
		 nbpcd="0"
		 countrycode="44"
		 sid="22656 to 22911"
		 gmt="0"
		 gmtdst="1"
		 sidconflict=""
	/>

	<ad country="United States of America"
		 mcc="310 to 316"
		 idd="011"
		 ndd="1"
		 nanp="NANP"
		 nbpcd="0"
		 countrycode="1"
		 sid="1 to 2175	2304 to 7679	21567 to 21630"
		 gmt="-10 to -5"
		 gmtdst="-10 to -4"
		 sidconflict="1	2	3	7	13	23	27	29	33	43	47	61	65	67	69	71	111	131	211	257	259	261	263	311	320	322	326	328	330	387	389	389	391	395	576	582	703	739	741	1111	1112	1113	1218	1220	1222	1235	1282	1313	1315	1329	1409	1443	1521	1569	1581	1634	1666	1668	1700	1901	2177	2179	2181	2183	2185	2187	2189	2191	2193	2195	2197	2199	2201	2203	2205	2207	2209	2211	2213	2215	2217	2219	2221	2223	2225	2227	2229	2231	2233	2235	2237	2239	2241	2243	2301	2303	4110	4369	4370	4371	4120	4130	4140	5732	5734	5772	8294	8358	8360	8616	8860	8861	8863	8950	8952	8960	8962	9080	9212	9244	9426	9322	9394	9488	9562	9640	9642	9644	9788	9790"
	/>

	<ad country="United States Virgin Islands (US)"
		 mcc="332"
		 idd="011"
		 ndd="1"
		 nanp="NANP"
		 nbpcd="0"
		 countrycode="1"
		 sid="n/a"
		 gmt="-4"
		 gmtdst="-4"
		 sidconflict=""
	/>

	<ad country="Uruguay"
		 mcc="748"
		 idd="00"
		 ndd="0"
		 nanp=""
		 nbpcd="0"
		 countrycode="598"
		 sid="31168 to 31199"
		 gmt="-3"
		 gmtdst="-2"
		 sidconflict=""
	/>

	<ad country="Uzbekistan"
		 mcc="434"
		 idd="810"
		 ndd="8"
		 nanp=""
		 nbpcd="0"
		 countrycode="998"
		 sid="10832 to 10855	11555	11600"
		 gmt="5"
		 gmtdst="5"
		 sidconflict=""
	/>

	<ad country="Vanuatu"
		 mcc="541"
		 idd="00"
		 ndd="None"
		 nanp=""
		 nbpcd="0"
		 countrycode="678"
		 sid="10944 to 10959"
		 gmt="11"
		 gmtdst="12"
		 sidconflict=""
	/>

	<ad country="Vatican City State"
		 mcc="225"
		 idd="00"
		 ndd="None"
		 nanp=""
		 nbpcd="0"
		 countrycode="39"
		 sid="n/a"
		 gmt="1"
		 gmtdst="2"
		 sidconflict=""
	/>

	<ad country="Venezuela"
		 mcc="734"
		 idd="00"
		 ndd="0"
		 nanp=""
		 nbpcd="0"
		 countrycode="58"
		 sid="31488 to 31615"
		 gmt="-4.5"
		 gmtdst="-4.5"
		 sidconflict="4100	4120	4130	4140	4101	4150"
	/>

	<ad country="Vietnam"
		 mcc="452"
		 idd="00"
		 ndd="0"
		 nanp=""
		 nbpcd="0"
		 countrycode="84"
		 sid="13312 to 13439"
		 gmt="7"
		 gmtdst="7"
		 sidconflict=""
	/>

	<ad country="Wallis and Futuna (France)"
		 mcc="543"
		 idd="19"
		 ndd="None"
		 nanp=""
		 nbpcd="0"
		 countrycode="681"
		 sid="10992 to 11007"
		 gmt="12"
		 gmtdst="12"
		 sidconflict=""
	/>

	<ad country="Yemen"
		 mcc="421"
		 idd="00"
		 ndd="0"
		 nanp=""
		 nbpcd="0"
		 countrycode="967"
		 sid="11328 to 11343	11360 to 11375"
		 gmt="3"
		 gmtdst="3"
		 sidconflict=""
	/>

	<ad country="Zambia"
		 mcc="645"
		 idd="00"
		 ndd="0"
		 nanp=""
		 nbpcd="0"
		 countrycode="260"
		 sid="10016 to 10047"
		 gmt="2"
		 gmtdst="2"
		 sidconflict=""
	/>

	<ad country="Zimbabwe"
		 mcc="648"
		 idd="00"
		 ndd="0"
		 nanp=""
		 nbpcd="0"
		 countrycode="263"
		 sid="10080 to 10111"
		 gmt="2"
		 gmtdst="2"
		 sidconflict=""
	/>

	<ad country="Maritime"
		 mcc="901"
		 idd="011"
		 ndd="1"
		 nanp="NANP"
		 nbpcd="0"
		 countrycode="1"
		 sid="n/a"
		 gmt="n/a"
		 gmtdst="n/a"
		 sidconflict=""
	/>
</mccota>

